MANIFEST.in
README
setup.py
Flask_Edits.egg-info/PKG-INFO
Flask_Edits.egg-info/SOURCES.txt
Flask_Edits.egg-info/dependency_links.txt
Flask_Edits.egg-info/requires.txt
Flask_Edits.egg-info/top_level.txt
flask_edits/__init__.py
flask_edits/editable.py
flask_edits/views.py
flask_edits/static/bootstrap-switch/css/bootstrap-switch.min.css
flask_edits/static/bootstrap-switch/js/bootstrap-switch.min.js
flask_edits/static/bootstrap/css/bootstrap-theme.css
flask_edits/static/bootstrap/css/bootstrap-theme.css.map
flask_edits/static/bootstrap/css/bootstrap-theme.min.css
flask_edits/static/bootstrap/css/bootstrap.css
flask_edits/static/bootstrap/css/bootstrap.css.map
flask_edits/static/bootstrap/css/bootstrap.min.css
flask_edits/static/bootstrap/css/navbar.css
flask_edits/static/bootstrap/fonts/glyphicons-halflings-regular.eot
flask_edits/static/bootstrap/fonts/glyphicons-halflings-regular.svg
flask_edits/static/bootstrap/fonts/glyphicons-halflings-regular.ttf
flask_edits/static/bootstrap/fonts/glyphicons-halflings-regular.woff
flask_edits/static/bootstrap/js/bootstrap.js
flask_edits/static/bootstrap/js/bootstrap.min.js
flask_edits/static/summernote/summernote-bs3.css
flask_edits/static/summernote/summernote.css
flask_edits/static/summernote/summernote.min.js
flask_edits/templates/edits-admin.j2