Metadata-Version: 1.0
Name: Flask-Edits
Version: 0.8
Summary: Editable Content in Flask
Home-page: http://github.com/nathancahill/flask-edits
Author: Nathan Cahill
Author-email: nathan@nathancahill.com
License: BSD
Platform: UNKNOWN
